[{"path":"/francescobianco/tahoe","title":"Overview","count":9,"uniques":2},{"path":"/francescobianco/bulk","title":"Overview","count":2,"uniques":1},{"path":"/francescobianco/tahoe/blob/main/Manifest.toml","title":"/blob/main/Manifest.toml","count":1,"uniques":1},{"path":"/francescobianco/tahoe/commits","title":"/commits","count":1,"uniques":1},{"path":"/francescobianco/tahoe/tree/main","title":"/tree/main","count":1,"uniques":1},{"path":"/francescobianco/tahoe/tree/main/bin","title":"/tree/main/bin","count":1,"uniques":1}]